covid_detection/__init__.py
covid_detection/covid19.py
covid_detection/test.py
covid_detection-1.0.0.dist-info/METADATA
covid_detection-1.0.0.dist-info/WHEEL
covid_detection-1.0.0.dist-info/top_level.txt
covid_detection-1.0.0.dist-info/RECORD
