Metadata-Version: 2.1
Name: covid-detection
Version: 1.0.0
Summary: this a covid detection with audio ml model 
Home-page: https://github.com/jacktamin/king_libs
Author: Ahmad Dehghani
Author-email: ahd76money@gmail.com
License: MIT
Platform: UNKNOWN
Requires-Dist: librosa
